nonebot_plugin_tieba_monitor/__init__.py
nonebot_plugin_tieba_monitor/config.py
nonebot_plugin_tieba_monitor/filter.py
nonebot_plugin_tieba_monitor/notification.py
nonebot_plugin_tieba_monitor/tieba.py
nonebot_plugin_tieba_monitor-0.1.7.dist-info/licenses/LICENSE
nonebot_plugin_tieba_monitor-0.1.7.dist-info/METADATA
nonebot_plugin_tieba_monitor-0.1.7.dist-info/WHEEL
nonebot_plugin_tieba_monitor-0.1.7.dist-info/top_level.txt
nonebot_plugin_tieba_monitor-0.1.7.dist-info/RECORD
