Metadata-Version: 2.4
Name: nonebot-plugin-tieba-monitor
Version: 0.1.7
Summary: NoneBot2 plugin for monitoring Tieba forums
Author-email: su-liu-guang <wuhui0404@gmail.com>
License: GNU AGPLv3
Project-URL: Homepage, https://github.com/su-liu-guang/nonebot-plugin-tieba-monitor
Project-URL: Bug Tracker, https://github.com/su-liu-guang/nonebot-plugin-tieba-monitor/issues
Classifier: Programming Language :: Python :: 3
Classifier: License :: OSI Approved :: GNU Affero General Public License v3
Classifier: Operating System :: OS Independent
Classifier: Framework :: Robot Framework :: Library
Requires-Python: >=3.8
License-File: LICENSE
Requires-Dist: nonebot2>=2.3.0
Requires-Dist: nonebot-adapter-onebot>=2.2.3
Requires-Dist: nonebot-plugin-apscheduler>=0.3.0
Requires-Dist: aiotieba>=4.5.3
Requires-Dist: openai>=1.0.0
Requires-Dist: nonebot-plugin-localstore>=0.7.2
Dynamic: license-file
